Metadata-Version: 2.1
Name: ruben-anagram-solver
Version: 0.1.0
Summary: Simple command-line anagram solver
Home-page: https://github.com/Ruben9922/anagram-solver
Author: Ruben Dougall
Author-email: info.ruebz999@gmail.com
License: UNKNOWN
Keywords: anagram solver words strings command-line
Platform: UNKNOWN
Classifier: Programming Language :: Python :: 3
Classifier: License :: OSI Approved :: MIT License
Classifier: Operating System :: OS Independent
Classifier: Environment :: Console
Classifier: Natural Language :: English
Classifier: Topic :: Utilities
Requires-Python: >=3.6
License-File: LICENSE
